hollamundo.py
hollamundo-0.0.1.dist-info/LICENSE.txt
hollamundo-0.0.1.dist-info/METADATA
hollamundo-0.0.1.dist-info/WHEEL
hollamundo-0.0.1.dist-info/top_level.txt
hollamundo-0.0.1.dist-info/RECORD
