Metadata-Version: 2.1
Name: hollamundo
Version: 0.0.1
Summary: Say hello
Home-page: https://https://github.com/lcleofa/hollamundo
Author: lcleofa
License: UNKNOWN
Platform: UNKNOWN
Classifier: Programming Language :: Python :: 3
Classifier: Programming Language :: Python :: 3.6
Classifier: Programming Language :: Python :: 3.7
Classifier: Operating System :: OS Independent
